hybrie_py/__init__.py
hybrie_py/client.py
hybrie_py/exceptions.py
hybrie_py/models.py
hybrie_py/proto/__init__.py
hybrie_py/proto/hybrie_llm_pb2.py
hybrie_py/proto/hybrie_llm_pb2_grpc.py
hybrie_py/proto/hybrie_sdk_pb2.py
hybrie_py/proto/hybrie_sdk_pb2_grpc.py
hybrie_py-0.1.3.dist-info/METADATA
hybrie_py-0.1.3.dist-info/WHEEL
hybrie_py-0.1.3.dist-info/entry_points.txt
hybrie_py-0.1.3.dist-info/RECORD
