Metadata-Version: 2.4
Name: hybrie-py
Version: 0.1.3
Summary: Python SDK for HybrIE - Hybrid Inference Engine for Heterogeneous Hardware to Power Generative AI Models
Project-URL: Homepage, https://github.com/tosi-n/hybrie-py
Project-URL: Repository, https://github.com/tosi-n/hybrie-py
Project-URL: Documentation, https://github.com/tosi-n/hybrie-py#readme
Project-URL: Issues, https://github.com/tosi-n/hybrie-py/issues
Author: Tosin Dairo
License: MIT OR Apache-2.0
Keywords: AI,FLUX,LLM,ML,chat,diffusion,generative-ai,grpc,hybrid-inference,image-generation
Classifier: Development Status :: 4 - Beta
Classifier: Intended Audience :: Developers
Classifier: License :: OSI Approved :: Apache Software License
Classifier: License :: OSI Approved :: MIT License
Classifier: Programming Language :: Python :: 3
Classifier: Programming Language :: Python :: 3.9
Classifier: Programming Language :: Python :: 3.10
Classifier: Programming Language :: Python :: 3.11
Classifier: Programming Language :: Python :: 3.12
Classifier: Programming Language :: Python :: 3.13
Classifier: Topic :: Scientific/Engineering :: Artificial Intelligence
Classifier: Topic :: Software Development :: Libraries :: Python Modules
Requires-Python: >=3.9
Requires-Dist: aiofiles>=23.0.0
Requires-Dist: grpcio-tools>=1.54.0
Requires-Dist: grpcio>=1.54.0
Requires-Dist: pillow>=9.0.0
Requires-Dist: protobuf>=4.21.0
Requires-Dist: typing-extensions>=4.0.0
Provides-Extra: dev
Requires-Dist: black>=23.0.0; extra == 'dev'
Requires-Dist: flake8>=6.0.0; extra == 'dev'
Requires-Dist: isort>=5.12.0; extra == 'dev'
Requires-Dist: mypy>=1.0.0; extra == 'dev'
Requires-Dist: pytest-asyncio>=0.21.0; extra == 'dev'
Requires-Dist: pytest-cov>=4.0.0; extra == 'dev'
Requires-Dist: pytest>=7.0.0; extra == 'dev'
Provides-Extra: examples
Requires-Dist: jupyter>=1.0.0; extra == 'examples'
Requires-Dist: matplotlib>=3.5.0; extra == 'examples'
Requires-Dist: tqdm>=4.64.0; extra == 'examples'
